ethmeet/__init__.py
ethmeet/attend/__init__.py
ethmeet/attend/attend.py
ethmeet/attend/attendGoogle.py
ethmeet/attend/attendZoom.py
ethmeet/create/__init__.py
ethmeet/create/create.py
ethmeet/driver/__init__.py
ethmeet/driver/driver.py
ethmeet/login/__init__.py
ethmeet/login/login.py
ethmeet-1.7.1.data/scripts/gecko_install.py
ethmeet-1.7.1.dist-info/LICENSE
ethmeet-1.7.1.dist-info/METADATA
ethmeet-1.7.1.dist-info/WHEEL
ethmeet-1.7.1.dist-info/top_level.txt
ethmeet-1.7.1.dist-info/RECORD
